<?xml version="1.0" encoding="UTF-8"?>
<mosahebe>
 <code>5b6dbdc53eb695b6dbdc53ee75</code>
 <title>علی محمد زاده</title>
 <birthday>۱۶ آذر ۱۳۶۵</birthday>
 <Mokhtasar>رئیس مرکز تحقیقات سیاستگذاری اقتصاد سلامت دانشگاه علوم پزشکی آزاد اسلامی تهران با تاکید بر اینکه عوارض ناشی از سوختگی برای فرد و جامعه کمرشکن،.......</Mokhtasar>
 <dastebandi>آزاد</dastebandi>
 <image>../images/mosahebe/5b6dbdc540530636535896456898048.jpg</image>
 <data>&lt;h2 style=&quot;text-align: center;&quot;&gt;&lt;span style=&quot;color: rgb(147, 101, 184);&quot;&gt;رئیس مرکز تحقیقات سیاستگذاری اقتصاد سلامت دانشگاه علوم پزشکی آزاد اسلامی تهران با تاکید بر اینکه عوارض ناشی از سوختگی برای فرد و جامعه کمرشکن، فاجعه بار و خانمانسوز است گفت: سرمایه گذاری اساسی مسئولان پیشگیری از سوختگی با اختصاص منابع بیشتراست.&lt;/span&gt;&lt;/h2&gt;&lt;p&gt;&lt;span style=&quot;color: rgb(0, 0, 0);&quot;&gt;به گزارش خبرنگار خبرگزاری آنا، خلیل علی محمدزاده در هفتمین کنگره کشوری سوختگی با تشریح جوانب مختلف رابطه سوختگی و اقتصادتصریح کرد:&amp;laquo;سوختگی بیشتر در اقشار فقیر، حوادث شغلی و مناطق محروم و مرزی اتفاق می افتد و هزینه های سوختگی منجر به بستری و عوارض ناشی از آن، کمرشکن، فاجعه بار و خانمانسوز است.&amp;raquo;&lt;/span&gt;&lt;/p&gt;&lt;p&gt;&lt;span style=&quot;color: rgb(0, 0, 0);&quot;&gt;وی اقتصادی&amp;zwnj;ترین راه در کاهش سوختگی را پیشگیری از آن عنوان کرد و گفت: &amp;laquo;پیشگیری از هر بیماری و عارضه&amp;zwnj;ای مقدم بر درمان است ولی پیشگیری همیشه ارزان نیست.&amp;raquo;&lt;/span&gt;&lt;/p&gt;</data>
 <description></description>
 <kewords></kewords>
 <seotitle></seotitle>
</mosahebe>
